MANIFEST.in
README.md
README.rst
hello52
hello52.json
setup.cfg
setup.py
src/hello52/__init__.py
src/hello52/__main__.py
src/hello52/run.py
src/hello52/version.py
src/hello52.egg-info/PKG-INFO
src/hello52.egg-info/SOURCES.txt
src/hello52.egg-info/dependency_links.txt
src/hello52.egg-info/entry_points.txt
src/hello52.egg-info/requires.txt
src/hello52.egg-info/top_level.txt
src/hello52.egg-info/zip-safe
src/hello52/util/__init__.py
src/hello52/util/log.py